new.py
newparth-0.0.1.dist-info/LICENSE.txt
newparth-0.0.1.dist-info/METADATA
newparth-0.0.1.dist-info/WHEEL
newparth-0.0.1.dist-info/top_level.txt
newparth-0.0.1.dist-info/RECORD
