Metadata-Version: 2.1
Name: newparth
Version: 0.0.1
Summary: Say Hello
Home-page: https://github.com/paarthdani/testparth
Author: parth
Author-email: parth_dani@yahoo.in
License: UNKNOWN
Platform: UNKNOWN
